pyparlaclarin/__init__.py
pyparlaclarin/create.py
pyparlaclarin/read.py
pyparlaclarin/refine.py
pyparlaclarin-0.9.2.dist-info/METADATA
pyparlaclarin-0.9.2.dist-info/WHEEL
pyparlaclarin-0.9.2.dist-info/RECORD
