Metadata-Version: 2.1
Name: pyparlaclarin
Version: 0.9.2
Summary: Read, create, and modify Parla-Clarin XML files
Home-page: https://github.com/welfare-state-analytics/pyparlaclarin
License: MIT
Author: ninpnin
Author-email: vainoyrjanainen@icloud.com
Requires-Python: >=3.6,<4.0
Classifier: License :: OSI Approved :: MIT License
Classifier: Programming Language :: Python :: 3
Classifier: Programming Language :: Python :: 3.6
Classifier: Programming Language :: Python :: 3.7
Classifier: Programming Language :: Python :: 3.8
Classifier: Programming Language :: Python :: 3.9
Classifier: Programming Language :: Python :: 3.10
Classifier: Programming Language :: Python :: 3.11
Classifier: Programming Language :: Python :: 3.12
Classifier: Programming Language :: Python :: 3.13
Requires-Dist: lxml
Project-URL: Documentation, https://welfare-state-analytics.github.io/pyparlaclarin/pyparlaclarin/
Project-URL: Repository, https://github.com/welfare-state-analytics/pyparlaclarin
